{
    "file_name": "corrected_CAM_20231027073005_3_warped",
    "id": 16,
    "original_width": 582,
    "original_height": 490,
    "objects": [
        {
            "x": 23.7303664921466,
            "y": 5.772251308900524,
            "width": 65.41884816753927,
            "height": 43.61256544502618,
            "transcription": "F-",
            "label": "terminal_number"
        },
        {
            "x": 125.06544502617801,
            "y": 8.979057591623036,
            "width": 170.60209424083766,
            "height": 41.688481675392666,
            "transcription": "A6-별06",
            "label": "terminal_number"
        },
        {
            "x": 412.3952879581152,
            "y": 24.371727748691097,
            "width": 101.97643979057597,
            "height": 37.84031413612566,
            "transcription": "행당(대)",
            "label": "terminal_number"
        },
        {
            "x": 413.6780104712042,
            "y": 63.49476439790576,
            "width": 71.19109947643976,
            "height": 28.86125654450262,
            "transcription": "별06-",
            "label": "terminal_number"
        },
        {
            "x": 21.16492146596859,
            "y": 53.87434554973822,
            "width": 66.06020942408378,
            "height": 27.5785340314136,
            "transcription": "성동구",
            "label": "others"
        },
        {
            "x": 95.5628272251309,
            "y": 55.157068062827214,
            "width": 80.17015706806282,
            "height": 25.013089005235603,
            "transcription": "행당2동",
            "label": "others"
        },
        {
            "x": 486.79319371727746,
            "y": 56.43979057591623,
            "width": 73.11518324607327,
            "height": 36.55759162303665,
            "transcription": "이강훈",
            "label": "others"
        },
        {
            "x": 488.0759162303665,
            "y": 104.54188481675394,
            "width": 82.09424083769632,
            "height": 24.37172774869109,
            "transcription": "1588-2121",
            "label": "others"
        },
        {
            "x": 213.57329842931938,
            "y": 89.79057591623035,
            "width": 42.971204188481664,
            "height": 34.63350785340316,
            "transcription": "(신)",
            "label": "others"
        },
        {
            "x": 454.08376963350787,
            "y": 128.91361256544502,
            "width": 87.86649214659691,
            "height": 17.95811518324609,
            "transcription": "2023/10/24",
            "label": "others"
        },
        {
            "x": 443.8219895287959,
            "y": 327.0942408376963,
            "width": 93.63874345549735,
            "height": 21.164921465968643,
            "transcription": "2023/10/24",
            "label": "others"
        },
        {
            "x": 448.9528795811519,
            "y": 446.3874345549739,
            "width": 116.08638743455494,
            "height": 31.4267015706806,
            "transcription": "[157/500]",
            "label": "others"
        },
        {
            "x": 38.481675392670155,
            "y": 321.96335078534037,
            "width": 32.70942408376964,
            "height": 18.599476439790532,
            "transcription": "(신)",
            "label": "others"
        },
        {
            "x": 191.76701570680626,
            "y": 320.6806282722513,
            "width": 36.55759162303667,
            "height": 21.164921465968572,
            "transcription": "1-1",
            "label": "others"
        },
        {
            "x": 273.8612565445026,
            "y": 338.6387434554974,
            "width": 35.91623036649213,
            "height": 14.751308900523604,
            "transcription": "집하점",
            "label": "others"
        },
        {
            "x": 408.5471204188482,
            "y": 337.35602094240835,
            "width": 35.27486910994763,
            "height": 16.034031413612627,
            "transcription": "집하일",
            "label": "others"
        },
        {
            "x": 338.63874345549743,
            "y": 307.21204188481676,
            "width": 63.49476439790574,
            "height": 17.95811518324612,
            "transcription": "일반출고",
            "label": "others"
        },
        {
            "x": 417.5261780104712,
            "y": 307.85340314136124,
            "width": 132.1204188481675,
            "height": 17.958115183246054,
            "transcription": "2476-6814-5760",
            "label": "others"
        },
        {
            "x": 15.392670157068062,
            "y": 279.63350785340316,
            "width": 187.91884816753927,
            "height": 19.882198952879584,
            "transcription": "20 년 월 일 (인)",
            "label": "others"
        },
        {
            "x": 306.5706806282722,
            "y": 325.81151832460733,
            "width": 103.25916230366497,
            "height": 21.806282722513153,
            "transcription": "대전통성한(대)",
            "label": "others"
        },
        {
            "x": 7.696335078534031,
            "y": 331.58376963350787,
            "width": 28.219895287958117,
            "height": 20.523560209424062,
            "transcription": "운임",
            "label": "others"
        },
        {
            "x": 134.04450261780107,
            "y": 330.30104712041884,
            "width": 33.350785340314125,
            "height": 22.447643979057663,
            "transcription": "수량",
            "label": "others"
        },
        {
            "x": 11.544502617801047,
            "y": 94.28010471204188,
            "width": 172.5261780104712,
            "height": 25.013089005235603,
            "transcription": "2476-6814-5760",
            "label": "tracking_number"
        },
        {
            "x": 74.3979057591623,
            "y": 293.1020942408377,
            "width": 162.90575916230364,
            "height": 23.73036649214658,
            "transcription": "2476-6814-5760",
            "label": "tracking_number"
        },
        {
            "x": 12.185863874345552,
            "y": 304.0052356020942,
            "width": 60.287958115183244,
            "height": 21.164921465968643,
            "transcription": "운송장번호",
            "label": "tracking_number_key"
        },
        {
            "x": 5.772251308900524,
            "y": 397.00261780104717,
            "width": 29.502617801047126,
            "height": 23.089005235602034,
            "transcription": "품명",
            "label": "product_name_key"
        },
        {
            "x": 3.8481675392670156,
            "y": 461.1387434554974,
            "width": 31.426701570680635,
            "height": 19.24083769633511,
            "transcription": "비고",
            "label": "delivery_message_key"
        },
        {
            "x": 31.426701570680624,
            "y": 355.9554973821989,
            "width": 205.87696335078536,
            "height": 26.937172774869097,
            "transcription": "고객보상품(타월세트)/0개",
            "label": "product_name"
        },
        {
            "x": 422.6570680628272,
            "y": 104.54188481675394,
            "width": 62.853403141361234,
            "height": 21.16492146596859,
            "transcription": "롯데택배",
            "label": "company_name"
        },
        {
            "x": 193.0497382198953,
            "y": 238.58638743455495,
            "width": 128.27225130890054,
            "height": 19.882198952879584,
            "transcription": "033-739-1406",
            "label": "sender_phone_number"
        },
        {
            "x": 35.274869109947645,
            "y": 239.86910994764398,
            "width": 156.4921465968586,
            "height": 20.523560209424094,
            "transcription": "건강보험심사평가원 /",
            "label": "sender_name"
        },
        {
            "x": 7.054973821989529,
            "y": 245.0,
            "width": 28.219895287958117,
            "height": 25.654450261780145,
            "transcription": "보내는분",
            "label": "sender_key"
        },
        {
            "x": 7.054973821989529,
            "y": 141.7408376963351,
            "width": 19.88219895287958,
            "height": 96.2041884816754,
            "transcription": "받는분",
            "label": "recipient_key"
        },
        {
            "x": 33.35078534031413,
            "y": 155.85078534031413,
            "width": 45.53664921465969,
            "height": 25.654450261780113,
            "transcription": "허*은",
            "label": "recipient_name"
        },
        {
            "x": 30.785340314136125,
            "y": 123.1413612565445,
            "width": 303.36387434554973,
            "height": 31.426701570680642,
            "transcription": "서울숲행당푸르지오아파트",
            "label": "recipient_address_detail"
        },
        {
            "x": 422.6570680628272,
            "y": 181.50523560209425,
            "width": 82.09424083769632,
            "height": 22.447643979057595,
            "transcription": "서울숲행",
            "label": "recipient_address_detail"
        },
        {
            "x": 31.426701570680624,
            "y": 203.3115183246073,
            "width": 159.69895287958119,
            "height": 17.95811518324609,
            "transcription": "당푸르지오아파트)",
            "label": "recipient_address_detail"
        },
        {
            "x": 341.8455497382199,
            "y": 121.21727748691099,
            "width": 70.5497382198953,
            "height": 30.14397905759162,
            "transcription": "108동",
            "label": "recipient_address_building_number"
        },
        {
            "x": 237.9450261780105,
            "y": 181.50523560209425,
            "width": 55.798429319371756,
            "height": 19.882198952879584,
            "transcription": "108동",
            "label": "recipient_address_building_number"
        },
        {
            "x": 420.09162303664925,
            "y": 121.8586387434555,
            "width": 29.502617801047112,
            "height": 26.937172774869097,
            "transcription": "60",
            "label": "recipient_address_room_number"
        },
        {
            "x": 300.1570680628272,
            "y": 178.29842931937173,
            "width": 54.515706806282786,
            "height": 23.730366492146615,
            "transcription": "602호",
            "label": "recipient_address_room_number"
        },
        {
            "x": 356.59685863874347,
            "y": 178.29842931937173,
            "width": 65.41884816753924,
            "height": 23.730366492146615,
            "transcription": "(행당동,",
            "label": "recipient_address_dong"
        },
        {
            "x": 133.40314136125653,
            "y": 178.29842931937173,
            "width": 57.72251308900526,
            "height": 25.013089005235603,
            "transcription": "행당동",
            "label": "recipient_address_dong"
        },
        {
            "x": 195.61518324607331,
            "y": 203.3115183246073,
            "width": 87.86649214659683,
            "height": 21.164921465968607,
            "transcription": "(고산자로",
            "label": "recipient_address_ro_name"
        },
        {
            "x": 286.6884816753927,
            "y": 203.3115183246073,
            "width": 41.04712041884811,
            "height": 18.599476439790564,
            "transcription": "177)",
            "label": "recipient_address_ro_number"
        },
        {
            "x": 75.0392670157068,
            "y": 183.42931937172773,
            "width": 56.439790575916255,
            "height": 21.164921465968607,
            "transcription": "성동구",
            "label": "recipient_address_gu"
        },
        {
            "x": 29.50261780104712,
            "y": 183.42931937172773,
            "width": 40.40575916230366,
            "height": 21.164921465968607,
            "transcription": "서울",
            "label": "recipient_address_do"
        },
        {
            "x": 202.02879581151834,
            "y": 157.77486910994764,
            "width": 159.0575916230366,
            "height": 19.882198952879584,
            "transcription": "010-3702-3702",
            "label": "recipient_phone_number"
        },
        {
            "x": 384.175392670157,
            "y": 157.1335078534031,
            "width": 154.56806282722516,
            "height": 22.447643979057595,
            "transcription": "010-3702-3702",
            "label": "recipient_phone_number"
        },
        {
            "x": 326.4528795811519,
            "y": 201.38743455497382,
            "width": 138.53403141361255,
            "height": 21.806282722513085,
            "transcription": "[반송시 집하점]",
            "label": "others"
        }
    ]
}